kompos/__init__.py
kompos/komposconfig.py
kompos/main.py
kompos/parser.py
kompos/runner.py
kompos/data/config_schema.json
kompos/helpers/__init__.py
kompos/helpers/console.py
kompos/runners/__init__.py
kompos/runners/config.py
kompos/runners/explore.py
kompos/runners/helmfile.py
kompos/runners/terraform.py
kompos/runners/terraform_helper.py
kompos/runners/tfe.py
kompos/runners/validate.py
kompos-0.9.4.dist-info/licenses/LICENSE
kompos-0.9.4.dist-info/METADATA
kompos-0.9.4.dist-info/WHEEL
kompos-0.9.4.dist-info/entry_points.txt
kompos-0.9.4.dist-info/top_level.txt
kompos-0.9.4.dist-info/RECORD
