Metadata-Version: 2.4
Name: kompos
Version: 0.9.4
Summary: Kompos - cloud infrastructure automation
Home-page: https://github.com/adobe/kompos
Author: Adobe
Author-email: noreply@adobe.com
License: Apache2
Classifier: Development Status :: 5 - Production/Stable
Classifier: Environment :: Console
Classifier: Intended Audience :: Developers
Classifier: Intended Audience :: System Administrators
Classifier: License :: OSI Approved :: Apache Software License
Classifier: Operating System :: OS Independent
Classifier: Programming Language :: Python :: 3
Classifier: Programming Language :: Python :: 3.11
Classifier: Programming Language :: Python :: 3.12
Classifier: Programming Language :: Python :: Implementation :: CPython
Classifier: Topic :: Software Development :: Build Tools
Classifier: Topic :: System :: Systems Administration
Classifier: Topic :: Utilities
Requires-Python: >=3.11
License-File: LICENSE
Requires-Dist: setuptools>=40.0.0
Requires-Dist: packaging>=20.0
Requires-Dist: simpledi==0.4.1
Requires-Dist: PyYAML>=5.1
Requires-Dist: himl==0.19.0
Requires-Dist: fastjsonschema==2.14.*
Requires-Dist: termcolor>=1.1.0
Requires-Dist: kubeconfig>=1.1.1
Dynamic: author
Dynamic: author-email
Dynamic: classifier
Dynamic: description
Dynamic: description-content-type
Dynamic: home-page
Dynamic: license
Dynamic: license-file
Dynamic: requires-dist
Dynamic: requires-python
Dynamic: summary
